{
  "updatedUTC": "2026-04-23T09:14:20.925Z",
  "updatedIST": "Thu, 23 Apr 2026 14:44:20 IST",
  "count": 49,
  "summary": {
    "golden": 3,
    "death": 16,
    "bullish": 22,
    "watch": 0,
    "newToday": 0
  },
  "stocks": [
    {
      "symbol": "RELIANCE.NS",
      "name": "Reliance Industries",
      "sector": "Energy",
      "price": 1344.4,
      "priceChangePct": -1.3,
      "ma50": 1389.2,
      "ma200": 1438.69,
      "maGapPct": -3.44,
      "crossDate": "06 Mar 2026",
      "crossType": "death",
      "crossDaysAgo": 48,
      "trend": "🔻 Bearish",
      "isGoldenToday": false,
      "isDeathToday": false,
      "isBullish": false
    },
    {
      "symbol": "TCS.NS",
      "name": "TCS",
      "sector": "IT",
      "price": 2521.5,
      "priceChangePct": -0.67,
      "ma50": 2568.96,
      "ma200": 2989.28,
      "maGapPct": -14.061,
      "crossDate": "No recent crossover",
      "crossType": "none",
      "crossDaysAgo": null,
      "trend": "🔻 Bearish",
      "isGoldenToday": false,
      "isDeathToday": false,
      "isBullish": false
    },
    {
      "symbol": "HDFCBANK.NS",
      "name": "HDFC Bank",
      "sector": "Banking",
      "price": 785.75,
      "priceChangePct": -1.77,
      "ma50": 841.81,
      "ma200": 945.23,
      "maGapPct": -10.941,
      "crossDate": "No recent crossover",
      "crossType": "none",
      "crossDaysAgo": null,
      "trend": "🔻 Bearish",
      "isGoldenToday": false,
      "isDeathToday": false,
      "isBullish": false
    },
    {
      "symbol": "INFY.NS",
      "name": "Infosys",
      "sector": "IT",
      "price": 1243.2,
      "priceChangePct": -2,
      "ma50": 1315.76,
      "ma200": 1488.03,
      "maGapPct": -11.577,
      "crossDate": "05 Mar 2026",
      "crossType": "death",
      "crossDaysAgo": 49,
      "trend": "🔻 Bearish",
      "isGoldenToday": false,
      "isDeathToday": false,
      "isBullish": false
    },
    {
      "symbol": "ICICIBANK.NS",
      "name": "ICICI Bank",
      "sector": "Banking",
      "price": 1350.1,
      "priceChangePct": -1.28,
      "ma50": 1328.93,
      "ma200": 1379.58,
      "maGapPct": -3.672,
      "crossDate": "No recent crossover",
      "crossType": "none",
      "crossDaysAgo": null,
      "trend": "🔻 Bearish",
      "isGoldenToday": false,
      "isDeathToday": false,
      "isBullish": false
    },
    {
      "symbol": "HINDUNILVR.NS",
      "name": "Hindustan Unilever",
      "sector": "FMCG",
      "price": 2378.5,
      "priceChangePct": 0.41,
      "ma50": 2229.79,
      "ma200": 2404.98,
      "maGapPct": -7.284,
      "crossDate": "No recent crossover",
      "crossType": "none",
      "crossDaysAgo": null,
      "trend": "🔻 Bearish",
      "isGoldenToday": false,
      "isDeathToday": false,
      "isBullish": false
    },
    {
      "symbol": "ITC.NS",
      "name": "ITC",
      "sector": "FMCG",
      "price": 304.7,
      "priceChangePct": -0.26,
      "ma50": 308.49,
      "ma200": 373.82,
      "maGapPct": -17.474,
      "crossDate": "No recent crossover",
      "crossType": "none",
      "crossDaysAgo": null,
      "trend": "🔻 Bearish",
      "isGoldenToday": false,
      "isDeathToday": false,
      "isBullish": false
    },
    {
      "symbol": "SBIN.NS",
      "name": "State Bank of India",
      "sector": "Banking",
      "price": 1091.9,
      "priceChangePct": -1.03,
      "ma50": 1111.24,
      "ma200": 957.82,
      "maGapPct": 16.017,
      "crossDate": "No recent crossover",
      "crossType": "none",
      "crossDaysAgo": null,
      "trend": "🚀 Strong Bullish",
      "isGoldenToday": false,
      "isDeathToday": false,
      "isBullish": true
    },
    {
      "symbol": "BHARTIARTL.NS",
      "name": "Bharti Airtel",
      "sector": "Telecom",
      "price": 1839.3,
      "priceChangePct": 0.56,
      "ma50": 1885.51,
      "ma200": 1969.55,
      "maGapPct": -4.267,
      "crossDate": "16 Mar 2026",
      "crossType": "death",
      "crossDaysAgo": 38,
      "trend": "🔻 Bearish",
      "isGoldenToday": false,
      "isDeathToday": false,
      "isBullish": false
    },
    {
      "symbol": "KOTAKBANK.NS",
      "name": "Kotak Mahindra Bank",
      "sector": "Banking",
      "price": 370.05,
      "priceChangePct": -1.8,
      "ma50": 391.58,
      "ma200": 411.7,
      "maGapPct": -4.887,
      "crossDate": "13 Mar 2026",
      "crossType": "death",
      "crossDaysAgo": 41,
      "trend": "🔻 Bearish",
      "isGoldenToday": false,
      "isDeathToday": false,
      "isBullish": false
    },
    {
      "symbol": "LT.NS",
      "name": "Larsen and Toubro",
      "sector": "Infra",
      "price": 4038.5,
      "priceChangePct": 0.43,
      "ma50": 3931.5,
      "ma200": 3834.83,
      "maGapPct": 2.521,
      "crossDate": "No recent crossover",
      "crossType": "none",
      "crossDaysAgo": null,
      "trend": "📈 Bullish",
      "isGoldenToday": false,
      "isDeathToday": false,
      "isBullish": true
    },
    {
      "symbol": "BAJFINANCE.NS",
      "name": "Bajaj Finance",
      "sector": "Finance",
      "price": 919.35,
      "priceChangePct": -1.65,
      "ma50": 926.81,
      "ma200": 961.89,
      "maGapPct": -3.647,
      "crossDate": "12 Mar 2026",
      "crossType": "death",
      "crossDaysAgo": 42,
      "trend": "🔻 Bearish",
      "isGoldenToday": false,
      "isDeathToday": false,
      "isBullish": false
    },
    {
      "symbol": "HCLTECH.NS",
      "name": "HCL Technologies",
      "sector": "IT",
      "price": 1280,
      "priceChangePct": -0.41,
      "ma50": 1406.29,
      "ma200": 1524.14,
      "maGapPct": -7.732,
      "crossDate": "10 Mar 2026",
      "crossType": "death",
      "crossDaysAgo": 44,
      "trend": "🔻 Bearish",
      "isGoldenToday": false,
      "isDeathToday": false,
      "isBullish": false
    },
    {
      "symbol": "ASIANPAINT.NS",
      "name": "Asian Paints",
      "sector": "Paints",
      "price": 2515.7,
      "priceChangePct": -1.84,
      "ma50": 2327.92,
      "ma200": 2523.47,
      "maGapPct": -7.75,
      "crossDate": "13 Mar 2026",
      "crossType": "death",
      "crossDaysAgo": 41,
      "trend": "🔻 Bearish",
      "isGoldenToday": false,
      "isDeathToday": false,
      "isBullish": false
    },
    {
      "symbol": "AXISBANK.NS",
      "name": "Axis Bank",
      "sector": "Banking",
      "price": 1370.8,
      "priceChangePct": -0.64,
      "ma50": 1307.21,
      "ma200": 1221,
      "maGapPct": 7.061,
      "crossDate": "No recent crossover",
      "crossType": "none",
      "crossDaysAgo": null,
      "trend": "🚀 Strong Bullish",
      "isGoldenToday": false,
      "isDeathToday": false,
      "isBullish": true
    },
    {
      "symbol": "MARUTI.NS",
      "name": "Maruti Suzuki",
      "sector": "Auto",
      "price": 13144,
      "priceChangePct": -1.45,
      "ma50": 13787.5,
      "ma200": 14795.9,
      "maGapPct": -6.815,
      "crossDate": "23 Mar 2026",
      "crossType": "death",
      "crossDaysAgo": 31,
      "trend": "🔻 Bearish",
      "isGoldenToday": false,
      "isDeathToday": false,
      "isBullish": false
    },
    {
      "symbol": "TITAN.NS",
      "name": "Titan Company",
      "sector": "Consumer",
      "price": 4448.9,
      "priceChangePct": -0.13,
      "ma50": 4237.39,
      "ma200": 3850.4,
      "maGapPct": 10.051,
      "crossDate": "No recent crossover",
      "crossType": "none",
      "crossDaysAgo": null,
      "trend": "🚀 Strong Bullish",
      "isGoldenToday": false,
      "isDeathToday": false,
      "isBullish": true
    },
    {
      "symbol": "WIPRO.NS",
      "name": "Wipro",
      "sector": "IT",
      "price": 203.02,
      "priceChangePct": -0.48,
      "ma50": 203.2,
      "ma200": 239.15,
      "maGapPct": -15.032,
      "crossDate": "18 Feb 2026",
      "crossType": "death",
      "crossDaysAgo": 64,
      "trend": "🔻 Bearish",
      "isGoldenToday": false,
      "isDeathToday": false,
      "isBullish": false
    },
    {
      "symbol": "SUNPHARMA.NS",
      "name": "Sun Pharma",
      "sector": "Pharma",
      "price": 1687.2,
      "priceChangePct": 1.04,
      "ma50": 1735.73,
      "ma200": 1697.89,
      "maGapPct": 2.229,
      "crossDate": "No recent crossover",
      "crossType": "none",
      "crossDaysAgo": null,
      "trend": "📈 Bullish",
      "isGoldenToday": false,
      "isDeathToday": false,
      "isBullish": true
    },
    {
      "symbol": "ULTRACEMCO.NS",
      "name": "UltraTech Cement",
      "sector": "Cement",
      "price": 12100,
      "priceChangePct": -0.76,
      "ma50": 11887.3,
      "ma200": 12105.98,
      "maGapPct": -1.806,
      "crossDate": "06 Apr 2026",
      "crossType": "death",
      "crossDaysAgo": 17,
      "trend": "💀 Death Cross (17d ago)",
      "isGoldenToday": false,
      "isDeathToday": false,
      "isBullish": false
    },
    {
      "symbol": "NESTLEIND.NS",
      "name": "Nestle India",
      "sector": "FMCG",
      "price": 1405.7,
      "priceChangePct": 0.71,
      "ma50": 1258.05,
      "ma200": 1235.01,
      "maGapPct": 1.866,
      "crossDate": "No recent crossover",
      "crossType": "none",
      "crossDaysAgo": null,
      "trend": "📈 Bullish",
      "isGoldenToday": false,
      "isDeathToday": false,
      "isBullish": true
    },
    {
      "symbol": "POWERGRID.NS",
      "name": "Power Grid",
      "sector": "Power",
      "price": 318.75,
      "priceChangePct": -0.31,
      "ma50": 300.34,
      "ma200": 284.49,
      "maGapPct": 5.573,
      "crossDate": "20 Mar 2026",
      "crossType": "golden",
      "crossDaysAgo": 34,
      "trend": "🚀 Strong Bullish",
      "isGoldenToday": false,
      "isDeathToday": false,
      "isBullish": true
    },
    {
      "symbol": "NTPC.NS",
      "name": "NTPC",
      "sector": "Power",
      "price": 402.65,
      "priceChangePct": -0.68,
      "ma50": 377.65,
      "ma200": 346.2,
      "maGapPct": 9.084,
      "crossDate": "No recent crossover",
      "crossType": "none",
      "crossDaysAgo": null,
      "trend": "🚀 Strong Bullish",
      "isGoldenToday": false,
      "isDeathToday": false,
      "isBullish": true
    },
    {
      "symbol": "TECHM.NS",
      "name": "Tech Mahindra",
      "sector": "IT",
      "price": 1425.5,
      "priceChangePct": -2.54,
      "ma50": 1434.36,
      "ma200": 1507.78,
      "maGapPct": -4.87,
      "crossDate": "19 Mar 2026",
      "crossType": "death",
      "crossDaysAgo": 35,
      "trend": "🔻 Bearish",
      "isGoldenToday": false,
      "isDeathToday": false,
      "isBullish": false
    },
    {
      "symbol": "ONGC.NS",
      "name": "ONGC",
      "sector": "Energy",
      "price": 285.45,
      "priceChangePct": 0.63,
      "ma50": 276.27,
      "ma200": 251.08,
      "maGapPct": 10.033,
      "crossDate": "No recent crossover",
      "crossType": "none",
      "crossDaysAgo": null,
      "trend": "🚀 Strong Bullish",
      "isGoldenToday": false,
      "isDeathToday": false,
      "isBullish": true
    },
    {
      "symbol": "JSWSTEEL.NS",
      "name": "JSW Steel",
      "sector": "Metal",
      "price": 1253,
      "priceChangePct": -0.82,
      "ma50": 1207.96,
      "ma200": 1142.46,
      "maGapPct": 5.733,
      "crossDate": "No recent crossover",
      "crossType": "none",
      "crossDaysAgo": null,
      "trend": "🚀 Strong Bullish",
      "isGoldenToday": false,
      "isDeathToday": false,
      "isBullish": true
    },
    {
      "symbol": "ADANIPORTS.NS",
      "name": "Adani Ports",
      "sector": "Logistics",
      "price": 1593.6,
      "priceChangePct": 0.31,
      "ma50": 1469.36,
      "ma200": 1440.24,
      "maGapPct": 2.022,
      "crossDate": "No recent crossover",
      "crossType": "none",
      "crossDaysAgo": null,
      "trend": "📈 Bullish",
      "isGoldenToday": false,
      "isDeathToday": false,
      "isBullish": true
    },
    {
      "symbol": "HINDALCO.NS",
      "name": "Hindalco Industries",
      "sector": "Metal",
      "price": 1040,
      "priceChangePct": 0.01,
      "ma50": 942.14,
      "ma200": 828.73,
      "maGapPct": 13.684,
      "crossDate": "No recent crossover",
      "crossType": "none",
      "crossDaysAgo": null,
      "trend": "🚀 Strong Bullish",
      "isGoldenToday": false,
      "isDeathToday": false,
      "isBullish": true
    },
    {
      "symbol": "COALINDIA.NS",
      "name": "Coal India",
      "sector": "Mining",
      "price": 449.65,
      "priceChangePct": 1.24,
      "ma50": 440.82,
      "ma200": 404.38,
      "maGapPct": 9.012,
      "crossDate": "No recent crossover",
      "crossType": "none",
      "crossDaysAgo": null,
      "trend": "🚀 Strong Bullish",
      "isGoldenToday": false,
      "isDeathToday": false,
      "isBullish": true
    },
    {
      "symbol": "BPCL.NS",
      "name": "BPCL",
      "sector": "Energy",
      "price": 310.15,
      "priceChangePct": -1.35,
      "ma50": 330.25,
      "ma200": 342,
      "maGapPct": -3.437,
      "crossDate": "08 Apr 2026",
      "crossType": "death",
      "crossDaysAgo": 15,
      "trend": "💀 Death Cross (15d ago)",
      "isGoldenToday": false,
      "isDeathToday": false,
      "isBullish": false
    },
    {
      "symbol": "TATASTEEL.NS",
      "name": "Tata Steel",
      "sector": "Metal",
      "price": 210.63,
      "priceChangePct": -1.13,
      "ma50": 201.82,
      "ma200": 178.81,
      "maGapPct": 12.865,
      "crossDate": "No recent crossover",
      "crossType": "none",
      "crossDaysAgo": null,
      "trend": "🚀 Strong Bullish",
      "isGoldenToday": false,
      "isDeathToday": false,
      "isBullish": true
    },
    {
      "symbol": "GRASIM.NS",
      "name": "Grasim Industries",
      "sector": "Cement",
      "price": 2734.4,
      "priceChangePct": -1.52,
      "ma50": 2745.58,
      "ma200": 2782.93,
      "maGapPct": -1.342,
      "crossDate": "24 Mar 2026",
      "crossType": "death",
      "crossDaysAgo": 30,
      "trend": "💀 Death Cross (30d ago)",
      "isGoldenToday": false,
      "isDeathToday": false,
      "isBullish": false
    },
    {
      "symbol": "CIPLA.NS",
      "name": "Cipla",
      "sector": "Pharma",
      "price": 1303.2,
      "priceChangePct": 5.41,
      "ma50": 1285.23,
      "ma200": 1452.62,
      "maGapPct": -11.523,
      "crossDate": "No recent crossover",
      "crossType": "none",
      "crossDaysAgo": null,
      "trend": "🔻 Bearish",
      "isGoldenToday": false,
      "isDeathToday": false,
      "isBullish": false
    },
    {
      "symbol": "EICHERMOT.NS",
      "name": "Eicher Motors",
      "sector": "Auto",
      "price": 7082,
      "priceChangePct": -2.05,
      "ma50": 7323.91,
      "ma200": 6837.32,
      "maGapPct": 7.117,
      "crossDate": "No recent crossover",
      "crossType": "none",
      "crossDaysAgo": null,
      "trend": "🚀 Strong Bullish",
      "isGoldenToday": false,
      "isDeathToday": false,
      "isBullish": true
    },
    {
      "symbol": "DRREDDY.NS",
      "name": "Dr Reddys Labs",
      "sector": "Pharma",
      "price": 1327.5,
      "priceChangePct": 9.08,
      "ma50": 1268.16,
      "ma200": 1256.38,
      "maGapPct": 0.938,
      "crossDate": "02 Apr 2026",
      "crossType": "golden",
      "crossDaysAgo": 21,
      "trend": "📈 Post Golden (21d ago)",
      "isGoldenToday": false,
      "isDeathToday": false,
      "isBullish": true
    },
    {
      "symbol": "BAJAJ-AUTO.NS",
      "name": "Bajaj Auto",
      "sector": "Auto",
      "price": 9483.5,
      "priceChangePct": -1.23,
      "ma50": 9495.89,
      "ma200": 9052.42,
      "maGapPct": 4.899,
      "crossDate": "No recent crossover",
      "crossType": "none",
      "crossDaysAgo": null,
      "trend": "🚀 Strong Bullish",
      "isGoldenToday": false,
      "isDeathToday": false,
      "isBullish": true
    },
    {
      "symbol": "HEROMOTOCO.NS",
      "name": "Hero MotoCorp",
      "sector": "Auto",
      "price": 5004,
      "priceChangePct": -3.57,
      "ma50": 5398.06,
      "ma200": 5365.24,
      "maGapPct": 0.612,
      "crossDate": "No recent crossover",
      "crossType": "none",
      "crossDaysAgo": null,
      "trend": "📈 Bullish",
      "isGoldenToday": false,
      "isDeathToday": false,
      "isBullish": true
    },
    {
      "symbol": "INDUSINDBK.NS",
      "name": "IndusInd Bank",
      "sector": "Banking",
      "price": 857.9,
      "priceChangePct": -1.4,
      "ma50": 868.4,
      "ma200": 832.08,
      "maGapPct": 4.366,
      "crossDate": "No recent crossover",
      "crossType": "none",
      "crossDaysAgo": null,
      "trend": "🚀 Strong Bullish",
      "isGoldenToday": false,
      "isDeathToday": false,
      "isBullish": true
    },
    {
      "symbol": "BRITANNIA.NS",
      "name": "Britannia Industries",
      "sector": "FMCG",
      "price": 5647.5,
      "priceChangePct": -1.43,
      "ma50": 5813.3,
      "ma200": 5860.05,
      "maGapPct": -0.798,
      "crossDate": "07 Apr 2026",
      "crossType": "death",
      "crossDaysAgo": 16,
      "trend": "💀 Death Cross (16d ago)",
      "isGoldenToday": false,
      "isDeathToday": false,
      "isBullish": false
    },
    {
      "symbol": "APOLLOHOSP.NS",
      "name": "Apollo Hospitals",
      "sector": "Healthcare",
      "price": 7775.5,
      "priceChangePct": 1.48,
      "ma50": 7550.73,
      "ma200": 7466.56,
      "maGapPct": 1.127,
      "crossDate": "13 Apr 2026",
      "crossType": "golden",
      "crossDaysAgo": 10,
      "trend": "🥇 Golden Cross (10d ago)",
      "isGoldenToday": false,
      "isDeathToday": false,
      "isBullish": true
    },
    {
      "symbol": "DIVISLAB.NS",
      "name": "Divis Laboratories",
      "sector": "Pharma",
      "price": 6373.5,
      "priceChangePct": 1.4,
      "ma50": 6173.17,
      "ma200": 6312.91,
      "maGapPct": -2.214,
      "crossDate": "No recent crossover",
      "crossType": "none",
      "crossDaysAgo": null,
      "trend": "🔻 Bearish",
      "isGoldenToday": false,
      "isDeathToday": false,
      "isBullish": false
    },
    {
      "symbol": "BAJAJFINSV.NS",
      "name": "Bajaj Finserv",
      "sector": "Finance",
      "price": 1794.7,
      "priceChangePct": -2.62,
      "ma50": 1860.85,
      "ma200": 1983.47,
      "maGapPct": -6.182,
      "crossDate": "No recent crossover",
      "crossType": "none",
      "crossDaysAgo": null,
      "trend": "🔻 Bearish",
      "isGoldenToday": false,
      "isDeathToday": false,
      "isBullish": false
    },
    {
      "symbol": "TATACONSUM.NS",
      "name": "Tata Consumer Prod",
      "sector": "FMCG",
      "price": 1181.1,
      "priceChangePct": 0.21,
      "ma50": 1107.6,
      "ma200": 1125.65,
      "maGapPct": -1.603,
      "crossDate": "01 Apr 2026",
      "crossType": "death",
      "crossDaysAgo": 22,
      "trend": "💀 Death Cross (22d ago)",
      "isGoldenToday": false,
      "isDeathToday": false,
      "isBullish": false
    },
    {
      "symbol": "HDFCLIFE.NS",
      "name": "HDFC Life Insurance",
      "sector": "Insurance",
      "price": 599.95,
      "priceChangePct": -0.68,
      "ma50": 653.21,
      "ma200": 732.81,
      "maGapPct": -10.862,
      "crossDate": "No recent crossover",
      "crossType": "none",
      "crossDaysAgo": null,
      "trend": "🔻 Bearish",
      "isGoldenToday": false,
      "isDeathToday": false,
      "isBullish": false
    },
    {
      "symbol": "SBILIFE.NS",
      "name": "SBI Life Insurance",
      "sector": "Insurance",
      "price": 1826.8,
      "priceChangePct": -3.08,
      "ma50": 1948.66,
      "ma200": 1923.42,
      "maGapPct": 1.312,
      "crossDate": "No recent crossover",
      "crossType": "none",
      "crossDaysAgo": null,
      "trend": "📈 Bullish",
      "isGoldenToday": false,
      "isDeathToday": false,
      "isBullish": true
    },
    {
      "symbol": "ADANIENT.NS",
      "name": "Adani Enterprises",
      "sector": "Conglomerate",
      "price": 2301.2,
      "priceChangePct": 1.79,
      "ma50": 2075.61,
      "ma200": 2293.79,
      "maGapPct": -9.512,
      "crossDate": "No recent crossover",
      "crossType": "none",
      "crossDaysAgo": null,
      "trend": "🔻 Bearish",
      "isGoldenToday": false,
      "isDeathToday": false,
      "isBullish": false
    },
    {
      "symbol": "M&M.NS",
      "name": "Mahindra and Mahindra",
      "sector": "Auto",
      "price": 3035.8,
      "priceChangePct": -3.62,
      "ma50": 3260.95,
      "ma200": 3438.05,
      "maGapPct": -5.151,
      "crossDate": "23 Mar 2026",
      "crossType": "death",
      "crossDaysAgo": 31,
      "trend": "🔻 Bearish",
      "isGoldenToday": false,
      "isDeathToday": false,
      "isBullish": false
    },
    {
      "symbol": "SHREECEM.NS",
      "name": "Shree Cement",
      "sector": "Cement",
      "price": 25370,
      "priceChangePct": -1.42,
      "ma50": 24942.1,
      "ma200": 27736.38,
      "maGapPct": -10.074,
      "crossDate": "No recent crossover",
      "crossType": "none",
      "crossDaysAgo": null,
      "trend": "🔻 Bearish",
      "isGoldenToday": false,
      "isDeathToday": false,
      "isBullish": false
    },
    {
      "symbol": "BEL.NS",
      "name": "Bharat Electronics",
      "sector": "Defence",
      "price": 449.7,
      "priceChangePct": 0.22,
      "ma50": 439.36,
      "ma200": 412.81,
      "maGapPct": 6.43,
      "crossDate": "No recent crossover",
      "crossType": "none",
      "crossDaysAgo": null,
      "trend": "🚀 Strong Bullish",
      "isGoldenToday": false,
      "isDeathToday": false,
      "isBullish": true
    }
  ]
}