{
  "updatedUTC": "2026-07-08T07:41:21.686Z",
  "updatedIST": "Wed, 08 Jul 2026 13:11:21 IST",
  "count": 49,
  "summary": {
    "golden": 6,
    "death": 2,
    "bullish": 23,
    "watch": 2,
    "newToday": 0
  },
  "stocks": [
    {
      "symbol": "RELIANCE.NS",
      "name": "Reliance Industries",
      "sector": "Energy",
      "price": 1290.1,
      "priceChangePct": -1.4,
      "ma50": 1337.73,
      "ma200": 1417.34,
      "maGapPct": -5.617,
      "crossDate": "No recent crossover",
      "crossType": "none",
      "crossDaysAgo": null,
      "trend": "🔻 Bearish",
      "isGoldenToday": false,
      "isDeathToday": false,
      "isBullish": false
    },
    {
      "symbol": "TCS.NS",
      "name": "TCS",
      "sector": "IT",
      "price": 2077.6,
      "priceChangePct": -0.88,
      "ma50": 2231.79,
      "ma200": 2747.6,
      "maGapPct": -18.773,
      "crossDate": "No recent crossover",
      "crossType": "none",
      "crossDaysAgo": null,
      "trend": "🔻 Bearish",
      "isGoldenToday": false,
      "isDeathToday": false,
      "isBullish": false
    },
    {
      "symbol": "HDFCBANK.NS",
      "name": "HDFC Bank",
      "sector": "Banking",
      "price": 826.9,
      "priceChangePct": -0.29,
      "ma50": 775.02,
      "ma200": 888.28,
      "maGapPct": -12.75,
      "crossDate": "No recent crossover",
      "crossType": "none",
      "crossDaysAgo": null,
      "trend": "🔻 Bearish",
      "isGoldenToday": false,
      "isDeathToday": false,
      "isBullish": false
    },
    {
      "symbol": "INFY.NS",
      "name": "Infosys",
      "sector": "IT",
      "price": 1072.4,
      "priceChangePct": 0.06,
      "ma50": 1131.28,
      "ma200": 1383.94,
      "maGapPct": -18.257,
      "crossDate": "No recent crossover",
      "crossType": "none",
      "crossDaysAgo": null,
      "trend": "🔻 Bearish",
      "isGoldenToday": false,
      "isDeathToday": false,
      "isBullish": false
    },
    {
      "symbol": "ICICIBANK.NS",
      "name": "ICICI Bank",
      "sector": "Banking",
      "price": 1396.3,
      "priceChangePct": -1.3,
      "ma50": 1302.62,
      "ma200": 1344.09,
      "maGapPct": -3.085,
      "crossDate": "No recent crossover",
      "crossType": "none",
      "crossDaysAgo": null,
      "trend": "🔻 Bearish",
      "isGoldenToday": false,
      "isDeathToday": false,
      "isBullish": false
    },
    {
      "symbol": "HINDUNILVR.NS",
      "name": "Hindustan Unilever",
      "sector": "FMCG",
      "price": 2166.9,
      "priceChangePct": -1.59,
      "ma50": 2199.26,
      "ma200": 2318.15,
      "maGapPct": -5.129,
      "crossDate": "No recent crossover",
      "crossType": "none",
      "crossDaysAgo": null,
      "trend": "🔻 Bearish",
      "isGoldenToday": false,
      "isDeathToday": false,
      "isBullish": false
    },
    {
      "symbol": "ITC.NS",
      "name": "ITC",
      "sector": "FMCG",
      "price": 284.55,
      "priceChangePct": -1.45,
      "ma50": 294.92,
      "ma200": 342.31,
      "maGapPct": -13.844,
      "crossDate": "No recent crossover",
      "crossType": "none",
      "crossDaysAgo": null,
      "trend": "🔻 Bearish",
      "isGoldenToday": false,
      "isDeathToday": false,
      "isBullish": false
    },
    {
      "symbol": "SBIN.NS",
      "name": "State Bank of India",
      "sector": "Banking",
      "price": 1034.9,
      "priceChangePct": -0.31,
      "ma50": 1007.97,
      "ma200": 1012.01,
      "maGapPct": -0.399,
      "crossDate": "06 Jul 2026",
      "crossType": "death",
      "crossDaysAgo": 2,
      "trend": "💀 Death Cross (2d ago)",
      "isGoldenToday": false,
      "isDeathToday": false,
      "isBullish": false
    },
    {
      "symbol": "BHARTIARTL.NS",
      "name": "Bharti Airtel",
      "sector": "Telecom",
      "price": 1889.7,
      "priceChangePct": -1.87,
      "ma50": 1852.57,
      "ma200": 1950.99,
      "maGapPct": -5.044,
      "crossDate": "No recent crossover",
      "crossType": "none",
      "crossDaysAgo": null,
      "trend": "🔻 Bearish",
      "isGoldenToday": false,
      "isDeathToday": false,
      "isBullish": false
    },
    {
      "symbol": "KOTAKBANK.NS",
      "name": "Kotak Mahindra Bank",
      "sector": "Banking",
      "price": 376,
      "priceChangePct": -1.49,
      "ma50": 388.55,
      "ma200": 406.02,
      "maGapPct": -4.302,
      "crossDate": "No recent crossover",
      "crossType": "none",
      "crossDaysAgo": null,
      "trend": "🔻 Bearish",
      "isGoldenToday": false,
      "isDeathToday": false,
      "isBullish": false
    },
    {
      "symbol": "LT.NS",
      "name": "Larsen and Toubro",
      "sector": "Infra",
      "price": 3971.3,
      "priceChangePct": -0.52,
      "ma50": 4030.27,
      "ma200": 3958.02,
      "maGapPct": 1.826,
      "crossDate": "01 Jun 2026",
      "crossType": "golden",
      "crossDaysAgo": 37,
      "trend": "📈 Bullish",
      "isGoldenToday": false,
      "isDeathToday": false,
      "isBullish": true
    },
    {
      "symbol": "BAJFINANCE.NS",
      "name": "Bajaj Finance",
      "sector": "Finance",
      "price": 1032,
      "priceChangePct": -1.01,
      "ma50": 942.93,
      "ma200": 968.6,
      "maGapPct": -2.651,
      "crossDate": "No recent crossover",
      "crossType": "none",
      "crossDaysAgo": null,
      "trend": "🔻 Bearish",
      "isGoldenToday": false,
      "isDeathToday": false,
      "isBullish": false
    },
    {
      "symbol": "HCLTECH.NS",
      "name": "HCL Technologies",
      "sector": "IT",
      "price": 1157.6,
      "priceChangePct": -0.91,
      "ma50": 1150.99,
      "ma200": 1426.53,
      "maGapPct": -19.315,
      "crossDate": "No recent crossover",
      "crossType": "none",
      "crossDaysAgo": null,
      "trend": "🔻 Bearish",
      "isGoldenToday": false,
      "isDeathToday": false,
      "isBullish": false
    },
    {
      "symbol": "ASIANPAINT.NS",
      "name": "Asian Paints",
      "sector": "Paints",
      "price": 2698,
      "priceChangePct": -2.07,
      "ma50": 2638.56,
      "ma200": 2565.1,
      "maGapPct": 2.864,
      "crossDate": "16 Jun 2026",
      "crossType": "golden",
      "crossDaysAgo": 22,
      "trend": "📈 Post Golden (22d ago)",
      "isGoldenToday": false,
      "isDeathToday": false,
      "isBullish": true
    },
    {
      "symbol": "AXISBANK.NS",
      "name": "Axis Bank",
      "sector": "Banking",
      "price": 1335.5,
      "priceChangePct": -0.31,
      "ma50": 1305.04,
      "ma200": 1276.8,
      "maGapPct": 2.212,
      "crossDate": "No recent crossover",
      "crossType": "none",
      "crossDaysAgo": null,
      "trend": "📈 Bullish",
      "isGoldenToday": false,
      "isDeathToday": false,
      "isBullish": true
    },
    {
      "symbol": "MARUTI.NS",
      "name": "Maruti Suzuki",
      "sector": "Auto",
      "price": 14295,
      "priceChangePct": -1.67,
      "ma50": 13446.92,
      "ma200": 14776.24,
      "maGapPct": -8.996,
      "crossDate": "No recent crossover",
      "crossType": "none",
      "crossDaysAgo": null,
      "trend": "🔻 Bearish",
      "isGoldenToday": false,
      "isDeathToday": false,
      "isBullish": false
    },
    {
      "symbol": "TITAN.NS",
      "name": "Titan Company",
      "sector": "Consumer",
      "price": 4617,
      "priceChangePct": 2.96,
      "ma50": 4253.69,
      "ma200": 4047.74,
      "maGapPct": 5.088,
      "crossDate": "No recent crossover",
      "crossType": "none",
      "crossDaysAgo": null,
      "trend": "🚀 Strong Bullish",
      "isGoldenToday": false,
      "isDeathToday": false,
      "isBullish": true
    },
    {
      "symbol": "WIPRO.NS",
      "name": "Wipro",
      "sector": "IT",
      "price": 174.8,
      "priceChangePct": 1.04,
      "ma50": 189.13,
      "ma200": 222.14,
      "maGapPct": -14.862,
      "crossDate": "No recent crossover",
      "crossType": "none",
      "crossDaysAgo": null,
      "trend": "🔻 Bearish",
      "isGoldenToday": false,
      "isDeathToday": false,
      "isBullish": false
    },
    {
      "symbol": "SUNPHARMA.NS",
      "name": "Sun Pharma",
      "sector": "Pharma",
      "price": 1888.2,
      "priceChangePct": -0.8,
      "ma50": 1840.99,
      "ma200": 1748.95,
      "maGapPct": 5.263,
      "crossDate": "No recent crossover",
      "crossType": "none",
      "crossDaysAgo": null,
      "trend": "🚀 Strong Bullish",
      "isGoldenToday": false,
      "isDeathToday": false,
      "isBullish": true
    },
    {
      "symbol": "ULTRACEMCO.NS",
      "name": "UltraTech Cement",
      "sector": "Cement",
      "price": 11519,
      "priceChangePct": -1.22,
      "ma50": 11463.86,
      "ma200": 11844.58,
      "maGapPct": -3.214,
      "crossDate": "No recent crossover",
      "crossType": "none",
      "crossDaysAgo": null,
      "trend": "🔻 Bearish",
      "isGoldenToday": false,
      "isDeathToday": false,
      "isBullish": false
    },
    {
      "symbol": "NESTLEIND.NS",
      "name": "Nestle India",
      "sector": "FMCG",
      "price": 1466.5,
      "priceChangePct": -0.49,
      "ma50": 1427.27,
      "ma200": 1302.17,
      "maGapPct": 9.607,
      "crossDate": "No recent crossover",
      "crossType": "none",
      "crossDaysAgo": null,
      "trend": "🚀 Strong Bullish",
      "isGoldenToday": false,
      "isDeathToday": false,
      "isBullish": true
    },
    {
      "symbol": "POWERGRID.NS",
      "name": "Power Grid",
      "sector": "Power",
      "price": 282.9,
      "priceChangePct": -0.51,
      "ma50": 294.77,
      "ma200": 286.42,
      "maGapPct": 2.914,
      "crossDate": "No recent crossover",
      "crossType": "none",
      "crossDaysAgo": null,
      "trend": "📈 Bullish",
      "isGoldenToday": false,
      "isDeathToday": false,
      "isBullish": true
    },
    {
      "symbol": "NTPC.NS",
      "name": "NTPC",
      "sector": "Power",
      "price": 350.55,
      "priceChangePct": -1.03,
      "ma50": 374.3,
      "ma200": 357.22,
      "maGapPct": 4.781,
      "crossDate": "No recent crossover",
      "crossType": "none",
      "crossDaysAgo": null,
      "trend": "🚀 Strong Bullish",
      "isGoldenToday": false,
      "isDeathToday": false,
      "isBullish": true
    },
    {
      "symbol": "TECHM.NS",
      "name": "Tech Mahindra",
      "sector": "IT",
      "price": 1432.9,
      "priceChangePct": -1.01,
      "ma50": 1445.43,
      "ma200": 1485.48,
      "maGapPct": -2.697,
      "crossDate": "No recent crossover",
      "crossType": "none",
      "crossDaysAgo": null,
      "trend": "🔻 Bearish",
      "isGoldenToday": false,
      "isDeathToday": false,
      "isBullish": false
    },
    {
      "symbol": "ONGC.NS",
      "name": "ONGC",
      "sector": "Energy",
      "price": 242.08,
      "priceChangePct": -0.86,
      "ma50": 265.97,
      "ma200": 259.03,
      "maGapPct": 2.682,
      "crossDate": "No recent crossover",
      "crossType": "none",
      "crossDaysAgo": null,
      "trend": "📈 Bullish",
      "isGoldenToday": false,
      "isDeathToday": false,
      "isBullish": true
    },
    {
      "symbol": "JSWSTEEL.NS",
      "name": "JSW Steel",
      "sector": "Metal",
      "price": 1234.4,
      "priceChangePct": -0.96,
      "ma50": 1270.93,
      "ma200": 1200.71,
      "maGapPct": 5.848,
      "crossDate": "No recent crossover",
      "crossType": "none",
      "crossDaysAgo": null,
      "trend": "🚀 Strong Bullish",
      "isGoldenToday": false,
      "isDeathToday": false,
      "isBullish": true
    },
    {
      "symbol": "ADANIPORTS.NS",
      "name": "Adani Ports",
      "sector": "Logistics",
      "price": 1832.2,
      "priceChangePct": -1.73,
      "ma50": 1790.5,
      "ma200": 1546.13,
      "maGapPct": 15.805,
      "crossDate": "No recent crossover",
      "crossType": "none",
      "crossDaysAgo": null,
      "trend": "🚀 Strong Bullish",
      "isGoldenToday": false,
      "isDeathToday": false,
      "isBullish": true
    },
    {
      "symbol": "HINDALCO.NS",
      "name": "Hindalco Industries",
      "sector": "Metal",
      "price": 975.65,
      "priceChangePct": -0.48,
      "ma50": 1044.29,
      "ma200": 920.02,
      "maGapPct": 13.508,
      "crossDate": "No recent crossover",
      "crossType": "none",
      "crossDaysAgo": null,
      "trend": "🚀 Strong Bullish",
      "isGoldenToday": false,
      "isDeathToday": false,
      "isBullish": true
    },
    {
      "symbol": "COALINDIA.NS",
      "name": "Coal India",
      "sector": "Mining",
      "price": 427.85,
      "priceChangePct": -0.26,
      "ma50": 455.96,
      "ma200": 423.89,
      "maGapPct": 7.566,
      "crossDate": "No recent crossover",
      "crossType": "none",
      "crossDaysAgo": null,
      "trend": "🚀 Strong Bullish",
      "isGoldenToday": false,
      "isDeathToday": false,
      "isBullish": true
    },
    {
      "symbol": "BPCL.NS",
      "name": "BPCL",
      "sector": "Energy",
      "price": 305.45,
      "priceChangePct": -2.71,
      "ma50": 301.15,
      "ma200": 335.14,
      "maGapPct": -10.14,
      "crossDate": "No recent crossover",
      "crossType": "none",
      "crossDaysAgo": null,
      "trend": "🔻 Bearish",
      "isGoldenToday": false,
      "isDeathToday": false,
      "isBullish": false
    },
    {
      "symbol": "TATASTEEL.NS",
      "name": "Tata Steel",
      "sector": "Metal",
      "price": 189.44,
      "priceChangePct": -0.18,
      "ma50": 203.81,
      "ma200": 190.38,
      "maGapPct": 7.057,
      "crossDate": "No recent crossover",
      "crossType": "none",
      "crossDaysAgo": null,
      "trend": "🚀 Strong Bullish",
      "isGoldenToday": false,
      "isDeathToday": false,
      "isBullish": true
    },
    {
      "symbol": "GRASIM.NS",
      "name": "Grasim Industries",
      "sector": "Cement",
      "price": 3176.8,
      "priceChangePct": -0.44,
      "ma50": 3068.63,
      "ma200": 2854.52,
      "maGapPct": 7.501,
      "crossDate": "28 May 2026",
      "crossType": "golden",
      "crossDaysAgo": 41,
      "trend": "🚀 Strong Bullish",
      "isGoldenToday": false,
      "isDeathToday": false,
      "isBullish": true
    },
    {
      "symbol": "CIPLA.NS",
      "name": "Cipla",
      "sector": "Pharma",
      "price": 1451.5,
      "priceChangePct": -1.41,
      "ma50": 1392.62,
      "ma200": 1414.51,
      "maGapPct": -1.548,
      "crossDate": "No recent crossover",
      "crossType": "none",
      "crossDaysAgo": null,
      "trend": "🔻 Bearish",
      "isGoldenToday": false,
      "isDeathToday": false,
      "isBullish": false
    },
    {
      "symbol": "EICHERMOT.NS",
      "name": "Eicher Motors",
      "sector": "Auto",
      "price": 7583.5,
      "priceChangePct": 0.63,
      "ma50": 7273.75,
      "ma200": 7198.19,
      "maGapPct": 1.05,
      "crossDate": "No recent crossover",
      "crossType": "none",
      "crossDaysAgo": null,
      "trend": "📈 Bullish",
      "isGoldenToday": false,
      "isDeathToday": false,
      "isBullish": true
    },
    {
      "symbol": "DRREDDY.NS",
      "name": "Dr Reddys Labs",
      "sector": "Pharma",
      "price": 1358.2,
      "priceChangePct": 0.27,
      "ma50": 1307.74,
      "ma200": 1268.6,
      "maGapPct": 3.086,
      "crossDate": "No recent crossover",
      "crossType": "none",
      "crossDaysAgo": null,
      "trend": "🚀 Strong Bullish",
      "isGoldenToday": false,
      "isDeathToday": false,
      "isBullish": true
    },
    {
      "symbol": "BAJAJ-AUTO.NS",
      "name": "Bajaj Auto",
      "sector": "Auto",
      "price": 10243,
      "priceChangePct": 2.06,
      "ma50": 10197.13,
      "ma200": 9487.02,
      "maGapPct": 7.485,
      "crossDate": "No recent crossover",
      "crossType": "none",
      "crossDaysAgo": null,
      "trend": "🚀 Strong Bullish",
      "isGoldenToday": false,
      "isDeathToday": false,
      "isBullish": true
    },
    {
      "symbol": "HEROMOTOCO.NS",
      "name": "Hero MotoCorp",
      "sector": "Auto",
      "price": 4961.3,
      "priceChangePct": -0.68,
      "ma50": 4977.15,
      "ma200": 5430.69,
      "maGapPct": -8.351,
      "crossDate": "No recent crossover",
      "crossType": "none",
      "crossDaysAgo": null,
      "trend": "🔻 Bearish",
      "isGoldenToday": false,
      "isDeathToday": false,
      "isBullish": false
    },
    {
      "symbol": "INDUSINDBK.NS",
      "name": "IndusInd Bank",
      "sector": "Banking",
      "price": 1028.4,
      "priceChangePct": 0.6,
      "ma50": 923.96,
      "ma200": 864.93,
      "maGapPct": 6.825,
      "crossDate": "No recent crossover",
      "crossType": "none",
      "crossDaysAgo": null,
      "trend": "🚀 Strong Bullish",
      "isGoldenToday": false,
      "isDeathToday": false,
      "isBullish": true
    },
    {
      "symbol": "BRITANNIA.NS",
      "name": "Britannia Industries",
      "sector": "FMCG",
      "price": 5378,
      "priceChangePct": -1.4,
      "ma50": 5333.5,
      "ma200": 5752.16,
      "maGapPct": -7.278,
      "crossDate": "No recent crossover",
      "crossType": "none",
      "crossDaysAgo": null,
      "trend": "🔻 Bearish",
      "isGoldenToday": false,
      "isDeathToday": false,
      "isBullish": false
    },
    {
      "symbol": "APOLLOHOSP.NS",
      "name": "Apollo Hospitals",
      "sector": "Healthcare",
      "price": 8794.5,
      "priceChangePct": -0.48,
      "ma50": 8306.76,
      "ma200": 7656.77,
      "maGapPct": 8.489,
      "crossDate": "No recent crossover",
      "crossType": "none",
      "crossDaysAgo": null,
      "trend": "🚀 Strong Bullish",
      "isGoldenToday": false,
      "isDeathToday": false,
      "isBullish": true
    },
    {
      "symbol": "DIVISLAB.NS",
      "name": "Divis Laboratories",
      "sector": "Pharma",
      "price": 6792.5,
      "priceChangePct": 0.31,
      "ma50": 6705.11,
      "ma200": 6394.15,
      "maGapPct": 4.863,
      "crossDate": "19 May 2026",
      "crossType": "golden",
      "crossDaysAgo": 50,
      "trend": "🚀 Strong Bullish",
      "isGoldenToday": false,
      "isDeathToday": false,
      "isBullish": true
    },
    {
      "symbol": "BAJAJFINSV.NS",
      "name": "Bajaj Finserv",
      "sector": "Finance",
      "price": 1884.6,
      "priceChangePct": -0.04,
      "ma50": 1770.41,
      "ma200": 1924.74,
      "maGapPct": -8.018,
      "crossDate": "No recent crossover",
      "crossType": "none",
      "crossDaysAgo": null,
      "trend": "🔻 Bearish",
      "isGoldenToday": false,
      "isDeathToday": false,
      "isBullish": false
    },
    {
      "symbol": "TATACONSUM.NS",
      "name": "Tata Consumer Prod",
      "sector": "FMCG",
      "price": 1104.4,
      "priceChangePct": -1.83,
      "ma50": 1151.28,
      "ma200": 1145.06,
      "maGapPct": 0.543,
      "crossDate": "03 Jun 2026",
      "crossType": "golden",
      "crossDaysAgo": 35,
      "trend": "📈 Bullish",
      "isGoldenToday": false,
      "isDeathToday": false,
      "isBullish": true
    },
    {
      "symbol": "HDFCLIFE.NS",
      "name": "HDFC Life Insurance",
      "sector": "Insurance",
      "price": 567.85,
      "priceChangePct": -0.8,
      "ma50": 589.56,
      "ma200": 684.33,
      "maGapPct": -13.849,
      "crossDate": "No recent crossover",
      "crossType": "none",
      "crossDaysAgo": null,
      "trend": "🔻 Bearish",
      "isGoldenToday": false,
      "isDeathToday": false,
      "isBullish": false
    },
    {
      "symbol": "SBILIFE.NS",
      "name": "SBI Life Insurance",
      "sector": "Insurance",
      "price": 1823.3,
      "priceChangePct": -0.49,
      "ma50": 1811.8,
      "ma200": 1919.4,
      "maGapPct": -5.606,
      "crossDate": "No recent crossover",
      "crossType": "none",
      "crossDaysAgo": null,
      "trend": "🔻 Bearish",
      "isGoldenToday": false,
      "isDeathToday": false,
      "isBullish": false
    },
    {
      "symbol": "ADANIENT.NS",
      "name": "Adani Enterprises",
      "sector": "Conglomerate",
      "price": 3114.7,
      "priceChangePct": 0.24,
      "ma50": 2858.95,
      "ma200": 2401.25,
      "maGapPct": 19.061,
      "crossDate": "28 May 2026",
      "crossType": "golden",
      "crossDaysAgo": 41,
      "trend": "🚀 Strong Bullish",
      "isGoldenToday": false,
      "isDeathToday": false,
      "isBullish": true
    },
    {
      "symbol": "M&M.NS",
      "name": "Mahindra and Mahindra",
      "sector": "Auto",
      "price": 3184.3,
      "priceChangePct": -0.53,
      "ma50": 3112.7,
      "ma200": 3390.11,
      "maGapPct": -8.183,
      "crossDate": "No recent crossover",
      "crossType": "none",
      "crossDaysAgo": null,
      "trend": "🔻 Bearish",
      "isGoldenToday": false,
      "isDeathToday": false,
      "isBullish": false
    },
    {
      "symbol": "SHREECEM.NS",
      "name": "Shree Cement",
      "sector": "Cement",
      "price": 26560,
      "priceChangePct": -0.26,
      "ma50": 25003.9,
      "ma200": 26247.65,
      "maGapPct": -4.739,
      "crossDate": "No recent crossover",
      "crossType": "none",
      "crossDaysAgo": null,
      "trend": "🔻 Bearish",
      "isGoldenToday": false,
      "isDeathToday": false,
      "isBullish": false
    },
    {
      "symbol": "BEL.NS",
      "name": "Bharat Electronics",
      "sector": "Defence",
      "price": 413.25,
      "priceChangePct": -1.41,
      "ma50": 419.02,
      "ma200": 420.66,
      "maGapPct": -0.388,
      "crossDate": "03 Jul 2026",
      "crossType": "death",
      "crossDaysAgo": 5,
      "trend": "💀 Death Cross (5d ago)",
      "isGoldenToday": false,
      "isDeathToday": false,
      "isBullish": false
    }
  ]
}