{
  "updatedUTC": "2026-04-07T06:47:44.736Z",
  "updatedIST": "Tue, 07 Apr 2026 12:17:44 IST",
  "count": 49,
  "summary": {
    "golden": 4,
    "death": 17,
    "bullish": 22,
    "watch": 4,
    "newToday": 0
  },
  "stocks": [
    {
      "symbol": "RELIANCE.NS",
      "name": "Reliance Industries",
      "sector": "Energy",
      "price": 1294.6,
      "priceChangePct": -0.77,
      "ma50": 1402.31,
      "ma200": 1445.42,
      "maGapPct": -2.982,
      "crossDate": "06 Mar 2026",
      "crossType": "death",
      "crossDaysAgo": 32,
      "trend": "🔻 Bearish",
      "isGoldenToday": false,
      "isDeathToday": false,
      "isBullish": false
    },
    {
      "symbol": "TCS.NS",
      "name": "TCS",
      "sector": "IT",
      "price": 2533.5,
      "priceChangePct": 2.41,
      "ma50": 2695.61,
      "ma200": 3037.86,
      "maGapPct": -11.266,
      "crossDate": "No recent crossover",
      "crossType": "none",
      "crossDaysAgo": null,
      "trend": "🔻 Bearish",
      "isGoldenToday": false,
      "isDeathToday": false,
      "isBullish": false
    },
    {
      "symbol": "HDFCBANK.NS",
      "name": "HDFC Bank",
      "sector": "Banking",
      "price": 766,
      "priceChangePct": -0.65,
      "ma50": 870.52,
      "ma200": 955.37,
      "maGapPct": -8.881,
      "crossDate": "No recent crossover",
      "crossType": "none",
      "crossDaysAgo": null,
      "trend": "🔻 Bearish",
      "isGoldenToday": false,
      "isDeathToday": false,
      "isBullish": false
    },
    {
      "symbol": "INFY.NS",
      "name": "Infosys",
      "sector": "IT",
      "price": 1329.3,
      "priceChangePct": 1.77,
      "ma50": 1388.6,
      "ma200": 1504.97,
      "maGapPct": -7.733,
      "crossDate": "05 Mar 2026",
      "crossType": "death",
      "crossDaysAgo": 33,
      "trend": "🔻 Bearish",
      "isGoldenToday": false,
      "isDeathToday": false,
      "isBullish": false
    },
    {
      "symbol": "ICICIBANK.NS",
      "name": "ICICI Bank",
      "sector": "Banking",
      "price": 1224.3,
      "priceChangePct": -0.58,
      "ma50": 1334.24,
      "ma200": 1384.26,
      "maGapPct": -3.613,
      "crossDate": "No recent crossover",
      "crossType": "none",
      "crossDaysAgo": null,
      "trend": "🔻 Bearish",
      "isGoldenToday": false,
      "isDeathToday": false,
      "isBullish": false
    },
    {
      "symbol": "HINDUNILVR.NS",
      "name": "Hindustan Unilever",
      "sector": "FMCG",
      "price": 2067.3,
      "priceChangePct": -0.84,
      "ma50": 2263.65,
      "ma200": 2408.93,
      "maGapPct": -6.031,
      "crossDate": "No recent crossover",
      "crossType": "none",
      "crossDaysAgo": null,
      "trend": "🔻 Bearish",
      "isGoldenToday": false,
      "isDeathToday": false,
      "isBullish": false
    },
    {
      "symbol": "ITC.NS",
      "name": "ITC",
      "sector": "FMCG",
      "price": 297.25,
      "priceChangePct": 0.81,
      "ma50": 311.74,
      "ma200": 380,
      "maGapPct": -17.963,
      "crossDate": "No recent crossover",
      "crossType": "none",
      "crossDaysAgo": null,
      "trend": "🔻 Bearish",
      "isGoldenToday": false,
      "isDeathToday": false,
      "isBullish": false
    },
    {
      "symbol": "SBIN.NS",
      "name": "State Bank of India",
      "sector": "Banking",
      "price": 1019.8,
      "priceChangePct": -1.25,
      "ma50": 1105.72,
      "ma200": 942.41,
      "maGapPct": 17.329,
      "crossDate": "No recent crossover",
      "crossType": "none",
      "crossDaysAgo": null,
      "trend": "🚀 Strong Bullish",
      "isGoldenToday": false,
      "isDeathToday": false,
      "isBullish": true
    },
    {
      "symbol": "BHARTIARTL.NS",
      "name": "Bharti Airtel",
      "sector": "Telecom",
      "price": 1808.1,
      "priceChangePct": 0.85,
      "ma50": 1914.21,
      "ma200": 1974.77,
      "maGapPct": -3.066,
      "crossDate": "16 Mar 2026",
      "crossType": "death",
      "crossDaysAgo": 22,
      "trend": "💀 Death Cross (22d ago)",
      "isGoldenToday": false,
      "isDeathToday": false,
      "isBullish": false
    },
    {
      "symbol": "KOTAKBANK.NS",
      "name": "Kotak Mahindra Bank",
      "sector": "Banking",
      "price": 360.6,
      "priceChangePct": 0.01,
      "ma50": 399.64,
      "ma200": 414.88,
      "maGapPct": -3.674,
      "crossDate": "13 Mar 2026",
      "crossType": "death",
      "crossDaysAgo": 25,
      "trend": "💀 Death Cross (25d ago)",
      "isGoldenToday": false,
      "isDeathToday": false,
      "isBullish": false
    },
    {
      "symbol": "LT.NS",
      "name": "Larsen and Toubro",
      "sector": "Infra",
      "price": 3711.7,
      "priceChangePct": -0.43,
      "ma50": 3902.61,
      "ma200": 3813.25,
      "maGapPct": 2.343,
      "crossDate": "No recent crossover",
      "crossType": "none",
      "crossDaysAgo": null,
      "trend": "📈 Bullish",
      "isGoldenToday": false,
      "isDeathToday": false,
      "isBullish": true
    },
    {
      "symbol": "BAJFINANCE.NS",
      "name": "Bajaj Finance",
      "sector": "Finance",
      "price": 853.65,
      "priceChangePct": 0.33,
      "ma50": 931.54,
      "ma200": 962.38,
      "maGapPct": -3.204,
      "crossDate": "12 Mar 2026",
      "crossType": "death",
      "crossDaysAgo": 26,
      "trend": "💀 Death Cross (26d ago)",
      "isGoldenToday": false,
      "isDeathToday": false,
      "isBullish": false
    },
    {
      "symbol": "HCLTECH.NS",
      "name": "HCL Technologies",
      "sector": "IT",
      "price": 1441.1,
      "priceChangePct": 2.69,
      "ma50": 1465.84,
      "ma200": 1540.74,
      "maGapPct": -4.861,
      "crossDate": "10 Mar 2026",
      "crossType": "death",
      "crossDaysAgo": 28,
      "trend": "💀 Death Cross (28d ago)",
      "isGoldenToday": false,
      "isDeathToday": false,
      "isBullish": false
    },
    {
      "symbol": "ASIANPAINT.NS",
      "name": "Asian Paints",
      "sector": "Paints",
      "price": 2174.5,
      "priceChangePct": -0.45,
      "ma50": 2348.26,
      "ma200": 2516.15,
      "maGapPct": -6.673,
      "crossDate": "13 Mar 2026",
      "crossType": "death",
      "crossDaysAgo": 25,
      "trend": "💀 Death Cross (25d ago)",
      "isGoldenToday": false,
      "isDeathToday": false,
      "isBullish": false
    },
    {
      "symbol": "AXISBANK.NS",
      "name": "Axis Bank",
      "sector": "Banking",
      "price": 1228.3,
      "priceChangePct": -1.37,
      "ma50": 1299.61,
      "ma200": 1213.14,
      "maGapPct": 7.127,
      "crossDate": "No recent crossover",
      "crossType": "none",
      "crossDaysAgo": null,
      "trend": "🚀 Strong Bullish",
      "isGoldenToday": false,
      "isDeathToday": false,
      "isBullish": true
    },
    {
      "symbol": "MARUTI.NS",
      "name": "Maruti Suzuki",
      "sector": "Auto",
      "price": 12661,
      "priceChangePct": -0.21,
      "ma50": 14146.32,
      "ma200": 14754.07,
      "maGapPct": -4.119,
      "crossDate": "23 Mar 2026",
      "crossType": "death",
      "crossDaysAgo": 15,
      "trend": "💀 Death Cross (15d ago)",
      "isGoldenToday": false,
      "isDeathToday": false,
      "isBullish": false
    },
    {
      "symbol": "TITAN.NS",
      "name": "Titan Company",
      "sector": "Consumer",
      "price": 4214.7,
      "priceChangePct": -0.74,
      "ma50": 4136.88,
      "ma200": 3800.57,
      "maGapPct": 8.849,
      "crossDate": "No recent crossover",
      "crossType": "none",
      "crossDaysAgo": null,
      "trend": "🚀 Strong Bullish",
      "isGoldenToday": false,
      "isDeathToday": false,
      "isBullish": true
    },
    {
      "symbol": "WIPRO.NS",
      "name": "Wipro",
      "sector": "IT",
      "price": 203.59,
      "priceChangePct": 3.19,
      "ma50": 210.5,
      "ma200": 242.47,
      "maGapPct": -13.185,
      "crossDate": "18 Feb 2026",
      "crossType": "death",
      "crossDaysAgo": 48,
      "trend": "🔻 Bearish",
      "isGoldenToday": false,
      "isDeathToday": false,
      "isBullish": false
    },
    {
      "symbol": "SUNPHARMA.NS",
      "name": "Sun Pharma",
      "sector": "Pharma",
      "price": 1722.4,
      "priceChangePct": 1.64,
      "ma50": 1726.92,
      "ma200": 1696.96,
      "maGapPct": 1.766,
      "crossDate": "No recent crossover",
      "crossType": "none",
      "crossDaysAgo": null,
      "trend": "📈 Bullish",
      "isGoldenToday": false,
      "isDeathToday": false,
      "isBullish": true
    },
    {
      "symbol": "ULTRACEMCO.NS",
      "name": "UltraTech Cement",
      "sector": "Cement",
      "price": 10850,
      "priceChangePct": -0.96,
      "ma50": 12056.52,
      "ma200": 12100.58,
      "maGapPct": -0.364,
      "crossDate": "06 Apr 2026",
      "crossType": "death",
      "crossDaysAgo": 1,
      "trend": "💀 Death Cross (1d ago)",
      "isGoldenToday": false,
      "isDeathToday": false,
      "isBullish": false
    },
    {
      "symbol": "NESTLEIND.NS",
      "name": "Nestle India",
      "sector": "FMCG",
      "price": 1213,
      "priceChangePct": -0.25,
      "ma50": 1260.59,
      "ma200": 1229.73,
      "maGapPct": 2.51,
      "crossDate": "No recent crossover",
      "crossType": "none",
      "crossDaysAgo": null,
      "trend": "📈 Bullish",
      "isGoldenToday": false,
      "isDeathToday": false,
      "isBullish": true
    },
    {
      "symbol": "POWERGRID.NS",
      "name": "Power Grid",
      "sector": "Power",
      "price": 294.8,
      "priceChangePct": -0.12,
      "ma50": 290.65,
      "ma200": 283.46,
      "maGapPct": 2.537,
      "crossDate": "20 Mar 2026",
      "crossType": "golden",
      "crossDaysAgo": 18,
      "trend": "📈 Post Golden (18d ago)",
      "isGoldenToday": false,
      "isDeathToday": false,
      "isBullish": true
    },
    {
      "symbol": "NTPC.NS",
      "name": "NTPC",
      "sector": "Power",
      "price": 367.6,
      "priceChangePct": 0.41,
      "ma50": 369.01,
      "ma200": 343.05,
      "maGapPct": 7.569,
      "crossDate": "09 Feb 2026",
      "crossType": "golden",
      "crossDaysAgo": 57,
      "trend": "🚀 Strong Bullish",
      "isGoldenToday": false,
      "isDeathToday": false,
      "isBullish": true
    },
    {
      "symbol": "TECHM.NS",
      "name": "Tech Mahindra",
      "sector": "IT",
      "price": 1480.2,
      "priceChangePct": 2.12,
      "ma50": 1487.67,
      "ma200": 1519.96,
      "maGapPct": -2.124,
      "crossDate": "19 Mar 2026",
      "crossType": "death",
      "crossDaysAgo": 19,
      "trend": "💀 Death Cross (19d ago)",
      "isGoldenToday": false,
      "isDeathToday": false,
      "isBullish": false
    },
    {
      "symbol": "ONGC.NS",
      "name": "ONGC",
      "sector": "Energy",
      "price": 284.5,
      "priceChangePct": 0.94,
      "ma50": 270.26,
      "ma200": 248.97,
      "maGapPct": 8.552,
      "crossDate": "05 Feb 2026",
      "crossType": "golden",
      "crossDaysAgo": 61,
      "trend": "🚀 Strong Bullish",
      "isGoldenToday": false,
      "isDeathToday": false,
      "isBullish": true
    },
    {
      "symbol": "JSWSTEEL.NS",
      "name": "JSW Steel",
      "sector": "Metal",
      "price": 1133.1,
      "priceChangePct": -0.04,
      "ma50": 1202.6,
      "ma200": 1130.17,
      "maGapPct": 6.408,
      "crossDate": "No recent crossover",
      "crossType": "none",
      "crossDaysAgo": null,
      "trend": "🚀 Strong Bullish",
      "isGoldenToday": false,
      "isDeathToday": false,
      "isBullish": true
    },
    {
      "symbol": "ADANIPORTS.NS",
      "name": "Adani Ports",
      "sector": "Logistics",
      "price": 1375.5,
      "priceChangePct": -0.84,
      "ma50": 1447.76,
      "ma200": 1432.84,
      "maGapPct": 1.041,
      "crossDate": "No recent crossover",
      "crossType": "none",
      "crossDaysAgo": null,
      "trend": "📈 Bullish",
      "isGoldenToday": false,
      "isDeathToday": false,
      "isBullish": true
    },
    {
      "symbol": "HINDALCO.NS",
      "name": "Hindalco Industries",
      "sector": "Metal",
      "price": 949.7,
      "priceChangePct": 2.4,
      "ma50": 931.08,
      "ma200": 809.91,
      "maGapPct": 14.96,
      "crossDate": "No recent crossover",
      "crossType": "none",
      "crossDaysAgo": null,
      "trend": "🚀 Strong Bullish",
      "isGoldenToday": false,
      "isDeathToday": false,
      "isBullish": true
    },
    {
      "symbol": "COALINDIA.NS",
      "name": "Coal India",
      "sector": "Mining",
      "price": 460.1,
      "priceChangePct": 0.12,
      "ma50": 438.37,
      "ma200": 401.58,
      "maGapPct": 9.161,
      "crossDate": "No recent crossover",
      "crossType": "none",
      "crossDaysAgo": null,
      "trend": "🚀 Strong Bullish",
      "isGoldenToday": false,
      "isDeathToday": false,
      "isBullish": true
    },
    {
      "symbol": "BPCL.NS",
      "name": "BPCL",
      "sector": "Energy",
      "price": 272.45,
      "priceChangePct": -2.24,
      "ma50": 342.83,
      "ma200": 342.77,
      "maGapPct": 0.019,
      "crossDate": "No recent crossover",
      "crossType": "none",
      "crossDaysAgo": null,
      "trend": "📈 Bullish",
      "isGoldenToday": false,
      "isDeathToday": false,
      "isBullish": true
    },
    {
      "symbol": "TATASTEEL.NS",
      "name": "Tata Steel",
      "sector": "Metal",
      "price": 194.86,
      "priceChangePct": -0.63,
      "ma50": 198.07,
      "ma200": 175.86,
      "maGapPct": 12.633,
      "crossDate": "No recent crossover",
      "crossType": "none",
      "crossDaysAgo": null,
      "trend": "🚀 Strong Bullish",
      "isGoldenToday": false,
      "isDeathToday": false,
      "isBullish": true
    },
    {
      "symbol": "GRASIM.NS",
      "name": "Grasim Industries",
      "sector": "Cement",
      "price": 2607.9,
      "priceChangePct": -0.25,
      "ma50": 2760.12,
      "ma200": 2784.6,
      "maGapPct": -0.879,
      "crossDate": "24 Mar 2026",
      "crossType": "death",
      "crossDaysAgo": 14,
      "trend": "💀 Death Cross (14d ago)",
      "isGoldenToday": false,
      "isDeathToday": false,
      "isBullish": false
    },
    {
      "symbol": "CIPLA.NS",
      "name": "Cipla",
      "sector": "Pharma",
      "price": 1204,
      "priceChangePct": 0.26,
      "ma50": 1306.36,
      "ma200": 1467.4,
      "maGapPct": -10.974,
      "crossDate": "No recent crossover",
      "crossType": "none",
      "crossDaysAgo": null,
      "trend": "🔻 Bearish",
      "isGoldenToday": false,
      "isDeathToday": false,
      "isBullish": false
    },
    {
      "symbol": "EICHERMOT.NS",
      "name": "Eicher Motors",
      "sector": "Auto",
      "price": 6512.5,
      "priceChangePct": -1.27,
      "ma50": 7307.4,
      "ma200": 6747.65,
      "maGapPct": 8.296,
      "crossDate": "No recent crossover",
      "crossType": "none",
      "crossDaysAgo": null,
      "trend": "🚀 Strong Bullish",
      "isGoldenToday": false,
      "isDeathToday": false,
      "isBullish": true
    },
    {
      "symbol": "DRREDDY.NS",
      "name": "Dr Reddys Labs",
      "sector": "Pharma",
      "price": 1200,
      "priceChangePct": -1.46,
      "ma50": 1265.41,
      "ma200": 1261,
      "maGapPct": 0.35,
      "crossDate": "02 Apr 2026",
      "crossType": "golden",
      "crossDaysAgo": 5,
      "trend": "🥇 Golden Cross (5d ago)",
      "isGoldenToday": false,
      "isDeathToday": false,
      "isBullish": true
    },
    {
      "symbol": "BAJAJ-AUTO.NS",
      "name": "Bajaj Auto",
      "sector": "Auto",
      "price": 8960,
      "priceChangePct": 0.2,
      "ma50": 9448.46,
      "ma200": 8981.31,
      "maGapPct": 5.201,
      "crossDate": "No recent crossover",
      "crossType": "none",
      "crossDaysAgo": null,
      "trend": "🚀 Strong Bullish",
      "isGoldenToday": false,
      "isDeathToday": false,
      "isBullish": true
    },
    {
      "symbol": "HEROMOTOCO.NS",
      "name": "Hero MotoCorp",
      "sector": "Auto",
      "price": 5011,
      "priceChangePct": -1.81,
      "ma50": 5471.74,
      "ma200": 5313.35,
      "maGapPct": 2.981,
      "crossDate": "No recent crossover",
      "crossType": "none",
      "crossDaysAgo": null,
      "trend": "📈 Bullish",
      "isGoldenToday": false,
      "isDeathToday": false,
      "isBullish": true
    },
    {
      "symbol": "INDUSINDBK.NS",
      "name": "IndusInd Bank",
      "sector": "Banking",
      "price": 778.3,
      "priceChangePct": -1,
      "ma50": 881.93,
      "ma200": 832.07,
      "maGapPct": 5.992,
      "crossDate": "No recent crossover",
      "crossType": "none",
      "crossDaysAgo": null,
      "trend": "🚀 Strong Bullish",
      "isGoldenToday": false,
      "isDeathToday": false,
      "isBullish": true
    },
    {
      "symbol": "BRITANNIA.NS",
      "name": "Britannia Industries",
      "sector": "FMCG",
      "price": 5520,
      "priceChangePct": -0.27,
      "ma50": 5856.88,
      "ma200": 5861.39,
      "maGapPct": -0.077,
      "crossDate": "07 Apr 2026",
      "crossType": "death",
      "crossDaysAgo": null,
      "trend": "💀 DEATH CROSS — TODAY!",
      "isGoldenToday": false,
      "isDeathToday": true,
      "isBullish": false
    },
    {
      "symbol": "APOLLOHOSP.NS",
      "name": "Apollo Hospitals",
      "sector": "Healthcare",
      "price": 7328,
      "priceChangePct": -0.61,
      "ma50": 7400.27,
      "ma200": 7439.44,
      "maGapPct": -0.526,
      "crossDate": "No recent crossover",
      "crossType": "none",
      "crossDaysAgo": null,
      "trend": "🔻 Bearish",
      "isGoldenToday": false,
      "isDeathToday": false,
      "isBullish": false
    },
    {
      "symbol": "DIVISLAB.NS",
      "name": "Divis Laboratories",
      "sector": "Pharma",
      "price": 5861.5,
      "priceChangePct": 0.7,
      "ma50": 6150.2,
      "ma200": 6337.74,
      "maGapPct": -2.959,
      "crossDate": "30 Jan 2026",
      "crossType": "death",
      "crossDaysAgo": 67,
      "trend": "🔻 Bearish",
      "isGoldenToday": false,
      "isDeathToday": false,
      "isBullish": false
    },
    {
      "symbol": "BAJAJFINSV.NS",
      "name": "Bajaj Finserv",
      "sector": "Finance",
      "price": 1665.7,
      "priceChangePct": -0.39,
      "ma50": 1893.66,
      "ma200": 1994.37,
      "maGapPct": -5.05,
      "crossDate": "06 Feb 2026",
      "crossType": "death",
      "crossDaysAgo": 60,
      "trend": "🔻 Bearish",
      "isGoldenToday": false,
      "isDeathToday": false,
      "isBullish": false
    },
    {
      "symbol": "TATACONSUM.NS",
      "name": "Tata Consumer Prod",
      "sector": "FMCG",
      "price": 1054.9,
      "priceChangePct": -0.03,
      "ma50": 1115.06,
      "ma200": 1124.97,
      "maGapPct": -0.881,
      "crossDate": "01 Apr 2026",
      "crossType": "death",
      "crossDaysAgo": 6,
      "trend": "💀 Death Cross (6d ago)",
      "isGoldenToday": false,
      "isDeathToday": false,
      "isBullish": false
    },
    {
      "symbol": "HDFCLIFE.NS",
      "name": "HDFC Life Insurance",
      "sector": "Insurance",
      "price": 577.5,
      "priceChangePct": -0.5,
      "ma50": 677.53,
      "ma200": 742.39,
      "maGapPct": -8.737,
      "crossDate": "No recent crossover",
      "crossType": "none",
      "crossDaysAgo": null,
      "trend": "🔻 Bearish",
      "isGoldenToday": false,
      "isDeathToday": false,
      "isBullish": false
    },
    {
      "symbol": "SBILIFE.NS",
      "name": "SBI Life Insurance",
      "sector": "Insurance",
      "price": 1827.4,
      "priceChangePct": -0.51,
      "ma50": 1969.53,
      "ma200": 1918.06,
      "maGapPct": 2.683,
      "crossDate": "No recent crossover",
      "crossType": "none",
      "crossDaysAgo": null,
      "trend": "📈 Bullish",
      "isGoldenToday": false,
      "isDeathToday": false,
      "isBullish": true
    },
    {
      "symbol": "ADANIENT.NS",
      "name": "Adani Enterprises",
      "sector": "Conglomerate",
      "price": 1876,
      "priceChangePct": -1.38,
      "ma50": 2050.59,
      "ma200": 2313.31,
      "maGapPct": -11.357,
      "crossDate": "No recent crossover",
      "crossType": "none",
      "crossDaysAgo": null,
      "trend": "🔻 Bearish",
      "isGoldenToday": false,
      "isDeathToday": false,
      "isBullish": false
    },
    {
      "symbol": "M&M.NS",
      "name": "Mahindra and Mahindra",
      "sector": "Auto",
      "price": 2980.5,
      "priceChangePct": -1.36,
      "ma50": 3325.95,
      "ma200": 3435,
      "maGapPct": -3.175,
      "crossDate": "23 Mar 2026",
      "crossType": "death",
      "crossDaysAgo": 15,
      "trend": "💀 Death Cross (15d ago)",
      "isGoldenToday": false,
      "isDeathToday": false,
      "isBullish": false
    },
    {
      "symbol": "SHREECEM.NS",
      "name": "Shree Cement",
      "sector": "Cement",
      "price": 23315,
      "priceChangePct": -1.6,
      "ma50": 25430.3,
      "ma200": 27996.78,
      "maGapPct": -9.167,
      "crossDate": "No recent crossover",
      "crossType": "none",
      "crossDaysAgo": null,
      "trend": "🔻 Bearish",
      "isGoldenToday": false,
      "isDeathToday": false,
      "isBullish": false
    },
    {
      "symbol": "BEL.NS",
      "name": "Bharat Electronics",
      "sector": "Defence",
      "price": 425.65,
      "priceChangePct": -0.35,
      "ma50": 435.57,
      "ma200": 410.81,
      "maGapPct": 6.027,
      "crossDate": "No recent crossover",
      "crossType": "none",
      "crossDaysAgo": null,
      "trend": "🚀 Strong Bullish",
      "isGoldenToday": false,
      "isDeathToday": false,
      "isBullish": true
    }
  ]
}